odoo/addons/event_stage_cancelled/README.rst
odoo/addons/event_stage_cancelled/__init__.py
odoo/addons/event_stage_cancelled/__manifest__.py
odoo/addons/event_stage_cancelled/data/event_data.xml
odoo/addons/event_stage_cancelled/data/mail_template_data.xml
odoo/addons/event_stage_cancelled/i18n/es.po
odoo/addons/event_stage_cancelled/i18n/event_stage_cancelled.pot
odoo/addons/event_stage_cancelled/i18n/it.po
odoo/addons/event_stage_cancelled/models/__init__.py
odoo/addons/event_stage_cancelled/models/event_event.py
odoo/addons/event_stage_cancelled/models/event_mail.py
odoo/addons/event_stage_cancelled/models/event_registration.py
odoo/addons/event_stage_cancelled/models/event_stage.py
odoo/addons/event_stage_cancelled/models/event_type_mail.py
odoo/addons/event_stage_cancelled/readme/CONFIGURE.md
odoo/addons/event_stage_cancelled/readme/CONTEXT.md
odoo/addons/event_stage_cancelled/readme/CONTRIBUTORS.md
odoo/addons/event_stage_cancelled/readme/DESCRIPTION.md
odoo/addons/event_stage_cancelled/readme/ROADMAP.md
odoo/addons/event_stage_cancelled/readme/USAGE.md
odoo/addons/event_stage_cancelled/static/description/icon.png
odoo/addons/event_stage_cancelled/static/description/index.html
odoo/addons/event_stage_cancelled/tests/__init__.py
odoo/addons/event_stage_cancelled/tests/test_event_stage_cancelled.py
odoo/addons/event_stage_cancelled/views/event_event_views.xml
odoo/addons/event_stage_cancelled/views/event_stage_views.xml
odoo_addon_event_stage_cancelled-17.0.1.0.0.5.dist-info/METADATA
odoo_addon_event_stage_cancelled-17.0.1.0.0.5.dist-info/WHEEL
odoo_addon_event_stage_cancelled-17.0.1.0.0.5.dist-info/top_level.txt
odoo_addon_event_stage_cancelled-17.0.1.0.0.5.dist-info/RECORD
